{
  "name": "FireRed",
  "screen": {
    "sourcePosition": [8, 8],
    "sourceSize": [960, 640],
    "size": [240, 160],
    "dialogLines": [120, 121]
  },
  "sprite": {
    "size": [7, 14],
    "image": "resources/firered_tiles.png",
    "text": "resources/firered_tiles.txt",
    "colorMap": [[246, 1], [206, 2], [97, 3], [61, 3]]
  },
  "timestamp": {
    "position": [970, 48],
    "size": [165, 32],
    "characterMap": {
      "HHDCCCCCDHH":  "0",
      "CCKKJBB":      "1",
      "EEEEEEEDDEE":  "2",
      "CCDCDDDDEGG":  "3",
      "EEDDDDKKKBB":  "4",
      "GGEDDDDDEFF":  "5",
      "HHEDDDDDEEE":  "6",
      "BBBBFFHEEEE":  "7",
      "GGEDDDDDEGG":  "8",
      "EEEDDDDDEHH":  "9",
      "DDDCCCCCDII":  "d",
      "IIBBBBBBBEE":  "h",
      "FFBBFFFBBEE":  "m",
      "DDEDDDEDD":    "s"
    }
  }
}
